<?xml version="1.0" encoding="utf-8"?><Regulation lims:pit-date="2019-11-20" lims:lastAmendedDate="2019-11-20" lims:current-date="2019-12-03" lims:inforce-start-date="2019-11-20" lims:enacted-date="2019-11-20" lims:fid="1206327" lims:id="1206327" gazette-part="II" regulation-type="SI" xml:lang="en" xmlns:lims="http://justice.gc.ca/lims"><Identification lims:inforce-start-date="2019-11-20" lims:enacted-date="2019-11-20" lims:fid="1206328" lims:id="1206328"><InstrumentNumber>SI/2019-115</InstrumentNumber><RegistrationDate><Date><YYYY>2019</YYYY><MM>12</MM><DD>11</DD></Date></RegistrationDate><ConsolidationDate><Date><YYYY>2019</YYYY><MM>12</MM><DD>4</DD></Date></ConsolidationDate><EnablingAuthority lims:inforce-start-date="2019-11-20" lims:enacted-date="2019-11-20" lims:fid="1206329" lims:id="1206329"><XRefExternal reference-type="act" link="P-33.3">FEDERAL PUBLIC SECTOR LABOUR RELATIONS ACT</XRefExternal></EnablingAuthority><LongTitle lims:inforce-start-date="2019-11-20" lims:enacted-date="2019-11-20" lims:fid="1206330" lims:id="1206330">Order Designating the Minister of Public Works and Government Services as the Minister for the purposes of that Act</LongTitle><RegulationMakerOrder><RegulationMaker>P.C.</RegulationMaker><OrderNumber>2019-1353</OrderNumber><Date><YYYY>2019</YYYY><MM>11</MM><DD>20</DD></Date></RegulationMakerOrder></Identification><Order lims:inforce-start-date="2019-11-20" lims:enacted-date="2019-11-20" lims:fid="1206331" lims:id="1206331"><Provision lims:inforce-start-date="2019-11-20" lims:enacted-date="2019-11-20" lims:fid="1206332" lims:id="1206332" format-ref="indent-0-0" language-align="yes"><Text>Her Excellency the Governor General in Council, on the recommendation of the Prime Minister, pursuant to the definition <DefinitionRef>Minister</DefinitionRef> in subsection 2(1) of the <XRefExternal reference-type="act" link="P-33.3">Federal Public Sector Labour Relations Act</XRefExternal><FootnoteRef idref="fn_81000-3-1916_hq_26085">a</FootnoteRef>,</Text><Footnote id="fn_81000-3-1916_hq_26085" placement="page" status="official"><Label>a</Label><Text>S.C. 2003, c. 22, s. 2; S.C. 2017, c. 9, s. 2</Text></Footnote><Provision lims:inforce-start-date="2019-11-20" lims:enacted-date="2019-11-20" lims:fid="1206333" lims:id="1206333" format-ref="indent-1-1"><Label>(a)</Label><Text>repeals Order in Council P.C. 2019-390 of April 26, 2019<FootnoteRef idref="fn_81000-3-1926_hq_26086">b</FootnoteRef>; and</Text><Footnote id="fn_81000-3-1926_hq_26086" placement="page" status="official"><Label>b</Label><Text>SI/2019-23</Text></Footnote></Provision><Provision lims:inforce-start-date="2019-11-20" lims:enacted-date="2019-11-20" lims:fid="1206334" lims:id="1206334" format-ref="indent-1-1"><Label>(b)</Label><Text>designates the Minister of Public Works and Government Services, who is a member of the Queen’s Privy Council for Canada and is not a member of the Treasury Board, as the Minister for the purposes of that Act.</Text></Provision></Provision></Order></Regulation>