<?xml version="1.0" encoding="utf-8"?><Regulation lims:pit-date="2010-06-10" hasPreviousVersion="true" lims:lastAmendedDate="2010-06-10" lims:current-date="2019-06-21" lims:inforce-start-date="2010-06-10" lims:fid="539323" lims:id="539323" gazette-part="II" regulation-type="SOR" xml:lang="fr" xmlns:lims="http://justice.gc.ca/lims"><Identification lims:inforce-start-date="2010-06-10" lims:fid="539324" lims:id="539324"><InstrumentNumber>C.R.C., ch. 356</InstrumentNumber><ConsolidationDate lims:inforce-start-date="2010-06-10"><Date><YYYY>2019</YYYY><MM>6</MM><DD>22</DD></Date></ConsolidationDate><EnablingAuthority lims:inforce-start-date="2010-06-10" lims:fid="539326" lims:id="539326"><XRefExternal reference-type="act" link="A-12">LOI SUR LA PRÉVENTION DE LA POLLUTION DES EAUX ARCTIQUES</XRefExternal></EnablingAuthority><ShortTitle lims:inforce-start-date="2010-06-10" lims:fid="539327" lims:id="539327">Décret sur les zones de contrôle de la sécurité de la navigation</ShortTitle><LongTitle lims:inforce-start-date="2010-06-10" lims:fid="539328" lims:id="539328">Décret prescrivant certaines zones des eaux Arctiques à titre de zones de contrôle de la sécurité de la navigation</LongTitle></Identification><Body lims:inforce-start-date="2010-06-10" lims:fid="539329" lims:id="539329"><Heading lims:inforce-start-date="2010-06-10" lims:fid="539330" lims:id="539330" level="1"><TitleText>Titre abrégé</TitleText></Heading><Section lims:inforce-start-date="2006-03-22" lims:lastAmendedDate="2006-03-22" lims:fid="539331" lims:id="539331"><Label>1</Label><Text>Le présent décret peut être cité sous le titre : <XRefExternal reference-type="regulation" link="C.R.C.,_ch._356">Décret sur les zones de contrôle de la sécurité de la navigation</XRefExternal>.</Text></Section><Heading lims:inforce-start-date="2010-06-10" lims:fid="539332" lims:id="539332" level="1"><TitleText>Interprétation</TitleText></Heading><Section lims:inforce-start-date="2010-06-10" lims:lastAmendedDate="2010-06-10" lims:fid="539333" lims:id="539333"><Label>2</Label><Text>Dans le présent décret, <DefinedTermFr>limite au large</DefinedTermFr> s’entend de la limite extérieure de la zone économique exclusive du Canada. Toutefois, là où la frontière internationale entre le Canada et le Groenland est à moins de deux cents milles marins de la ligne de base de la mer territoriale du Canada, cette frontière internationale est substituée à cette limite extérieure.</Text><HistoricalNote><HistoricalNoteSubItem lims:inforce-start-date="2010-06-10" lims:fid="539335" lims:id="539335">DORS/2010-131, art. 1</HistoricalNoteSubItem></HistoricalNote></Section><Heading lims:inforce-start-date="2010-06-10" lims:fid="539336" lims:id="539336" level="1"><TitleText>Zones de contrôle de la sécurité de la navigation</TitleText></Heading><Section lims:inforce-start-date="2010-06-10" lims:lastAmendedDate="2010-06-10" lims:fid="539337" lims:id="539337"><Label>3</Label><Text>Les zones des eaux arctiques — autres que les rivières, les fleuves, les lacs ou autres plans d’eau douce — décrites à l’annexe 1 et qui figurent à l’annexe 2 sont désignées comme les zones de contrôle de la sécurité de la navigation.</Text><HistoricalNote><HistoricalNoteSubItem lims:inforce-start-date="2010-06-10" lims:fid="539339" lims:id="539339">DORS/2010-131, art. 1</HistoricalNoteSubItem></HistoricalNote></Section></Body><Schedule lims:inforce-start-date="2010-06-10" lims:lastAmendedDate="2010-06-10" lims:fid="539340" lims:id="539340" spanlanguages="no" bilingual="no"><ScheduleFormHeading lims:inforce-start-date="2010-06-10" lims:fid="539341" lims:id="539341"><Label>ANNEXE 1</Label><OriginatingRef>(article 3)</OriginatingRef></ScheduleFormHeading><Heading lims:inforce-start-date="2010-06-10" lims:fid="539342" lims:id="539342" level="1"><TitleText>Zone 1</TitleText></Heading><Provision lims:inforce-start-date="2010-06-10" lims:fid="539343" lims:id="539343" format-ref="indent-0-0" language-align="yes" list-item="no"><Text>Commençant au point 76°40′ de latitude, 99°00′ de longitude; de là, le long du parallèle 76°40′ de latitude jusqu’à 96°25′ de longitude; de là, le long d’une ligne jusqu’à 80°25′ de latitude, 88°00′ de longitude; de là, le long d’une ligne jusqu’au point d’intersection de 82°00′ de latitude avec la limite au large dans le détroit de Robeson; de là, le long de la limite au large vers le nord et vers le sud-ouest jusqu’à 141°00′ de longitude; de là, le long du méridien 141°00′ de longitude jusqu’à 71°20′ de latitude; de là, le long d’une ligne jusqu’à 71°15′ de latitude, 137°00′ de longitude; de là, le long d’une ligne jusqu’à 71°30′ de latitude, 134°00′ de longitude; de là, le long d’une ligne jusqu’à 72°00′ de latitude, 131°30′ de longitude; de là, le long d’une ligne jusqu’à 72°40′ de latitude, 131°00′ de longitude; de là, le long d’une ligne jusqu’au point d’intersection le plus à l’ouest de la latitude 74°20′ avec le littoral de l’île Banks, près du cap Prince Alfred; de là, le long du littoral nord et nord-est de l’île Banks jusqu’à son point d’intersection le plus à l’est avec la latitude 73°30′, près de la pointe Russell; de là, le long d’une ligne jusqu’à 74°30′ de latitude, 112°50′ de longitude; de là, le long d’une ligne jusqu’à 75°30′ de latitude, 106°10′ de longitude; de là, le long d’une ligne jusqu’à 75°50′ de latitude, 99°00′ de longitude; de là, le long du méridien 99°00′ de longitude jusqu’au point de départ.</Text></Provision><Heading lims:inforce-start-date="2010-06-10" lims:fid="539344" lims:id="539344" level="1"><TitleText>Zone 2</TitleText></Heading><Provision lims:inforce-start-date="2010-06-10" lims:fid="539345" lims:id="539345" format-ref="indent-0-0" language-align="yes" list-item="no"><Text>COMMENÇANT au point situé à 74°30′ de latitude, 99°00′ de longitude; DE LÀ le long du parallèle 74°30′ de latitude jusqu’à 112°50′ de longitude; DE LÀ le long d’une ligne jusqu’à l’intersection la plus à l’est de la latitude 73°30′ avec le littoral de l’île Banks, près de la pointe Russell; DE LÀ le long du littoral est de l’île Banks jusqu’à son intersection la plus à l’est avec la latitude 72°45′; DE LÀ le long du parallèle 72°45′ de latitude jusqu’à 117°20′ de longitude; DE LÀ le long d’une ligne jusqu’au point 70°00′ de latitude, 110°00′ de longitude; DE LÀ le long du parallèle 70°00′ de latitude jusqu’à 99°00′ de longitude; DE LÀ le long du méridien 99°00′ de longitude jusqu’au point de départ.</Text></Provision><Heading lims:inforce-start-date="2010-06-10" lims:fid="539346" lims:id="539346" level="1"><TitleText>Zone 3</TitleText></Heading><Provision lims:inforce-start-date="2010-06-10" lims:fid="539347" lims:id="539347" format-ref="indent-0-0" language-align="yes" list-item="no"><Text>COMMENÇANT au point 76°40′ de latitude, 96°25′ de longitude; DE LÀ le long du parallèle 76°40′ de latitude jusqu’à 88°30′ de longitude; DE LÀ le long d’une ligne jusqu’au point 79°15′ de latitude, 75°30′ de longitude; DE LÀ le long du parallèle 79°15′ de latitude jusqu’à la limite au large dans le détroit de Nares; DE LÀ le long de la limite au large jusqu’à 82°00′ de latitude dans le détroit de Robeson; DE LÀ le long d’une ligne jusqu’au point 80°25′ de latitude, 88°00′ de longitude; DE LÀ le long d’une ligne jusqu’au point de départ.</Text></Provision><Heading lims:inforce-start-date="2010-06-10" lims:fid="539348" lims:id="539348" level="1"><TitleText>Zone 4</TitleText></Heading><Provision lims:inforce-start-date="2010-06-10" lims:fid="539349" lims:id="539349" format-ref="indent-0-0" language-align="yes" list-item="no"><Text>Commençant au point 70°30′ de latitude, 141°00′ de longitude; de là, le long du parallèle 70°30′ de latitude jusqu’à 138°00′ de longitude; de là, le long d’une ligne jusqu’à 72°00′ de latitude, 127°00′ de longitude; de là, le long d’une ligne jusqu’à 73°30′ de latitude, 125°00′ de longitude; de là, le long du parallèle 73°30′ de latitude jusqu’à son point d’intersection le plus à l’ouest avec le littoral de l’île Banks, près de l’île Bernard; de là, le long du littoral ouest de l’île Banks jusqu’à son point d’intersection le plus à l’ouest avec 74°20′ de latitude, près du cap Prince Alfred; de là, le long d’une ligne jusqu’à 72°40′ de latitude, 131°00′ de longitude; de là, le long d’une ligne jusqu’à 72°00′ de latitude, 131°30′ de longitude; de là, le long d’une ligne jusqu’à 71°30′ de latitude, 134°00′ de longitude; de là, le long d’une ligne jusqu’à 71°15′ de latitude, 137°00′ de longitude; de là, le long d’une ligne jusqu’à 71°20′ de latitude, 141°00′ de longitude; de là, le long du méridien 141°00′ de longitude jusqu’au point de départ.</Text></Provision><Heading lims:inforce-start-date="2010-06-10" lims:fid="539350" lims:id="539350" level="1"><TitleText>Zone 5</TitleText></Heading><Provision lims:inforce-start-date="2010-06-10" lims:fid="539351" lims:id="539351" format-ref="indent-0-0" language-align="yes" list-item="no"><Text>COMMENÇANT au point 69°30′ de latitude, 84°00′ de longitude; DE LÀ le long du parallèle 69°30′ de latitude jusqu’à 93°20′ de longitude; DE LÀ le long du méridien 93°20′ de longitude jusqu’à 67°00′ de latitude; DE LÀ le long du parallèle 67°00′ de latitude jusqu’à 84°00′ de longitude; DE LÀ le long du méridien 84°00′ de longitude jusqu’au point de départ.</Text></Provision><Heading lims:inforce-start-date="2010-06-10" lims:fid="539352" lims:id="539352" level="1"><TitleText>Zone 6</TitleText></Heading><Provision lims:inforce-start-date="2010-06-10" lims:fid="539353" lims:id="539353" format-ref="indent-0-0" language-align="yes" list-item="no"><Text>COMMENÇANT au point 76°40′ de latitude, 99°00′ de longitude; DE LÀ le long du méridien 99°00′ de longitude jusqu’à 75°50′ de latitude; DE LÀ le long d’une ligne jusqu’au point 75°30′ de latitude, 106°10′ de longitude; DE LÀ le long d’une ligne jusqu’au point 74°30′ de latitude, 112°50′ de longitude; DE LÀ le long du parallèle 74°30′ de latitude jusqu’à 99°00′ de longitude; DE LÀ le long du méridien 99°00′ de longitude jusqu’à 70°00′ de latitude; DE LÀ le long du parallèle 70°00′ de latitude jusqu’à 93°20′ de longitude; DE LÀ le long du méridien 93°20′ de longitude jusqu’à 69°30′ de latitude; DE LÀ le long du parallèle 69°30′ de latitude jusqu’à 84°00′ de longitude; DE LÀ le long du méridien 84°00′ de longitude jusqu’à 70°50′ de latitude; DE LÀ le long du parallèle 70°50′ de latitude jusqu’à 87°00′ de longitude; DE LÀ le long du méridien 87°00′ de longitude jusqu’à 73°45′ de latitude; DE LÀ le long du parallèle 73°45′ de latitude jusqu’à 95°00′ de longitude; DE LÀ le long du méridien 95°00′ de longitude jusqu’à 75°00′ de latitude; DE LÀ le long du parallèle 75°00′ de latitude jusqu’à 82°00′ de longitude; DE LÀ le long d’une ligne jusqu’au point d’intersection de la latitude 76°30′ et de la limite au large dans la baie Baffin; DE LÀ le long de la limite au large jusqu’à 79°15′ de latitude dans le détroit de Nares; DE LÀ le long du parallèle 79°15′ de latitude jusqu’à 75°30′ de longitude; DE LÀ le long d’une ligne jusqu’au point 76°40′ de latitude, 88°30′ de longitude; DE LÀ le long du parallèle 76°40′ de latitude jusqu’au point de départ.</Text></Provision><Heading lims:inforce-start-date="2010-06-10" lims:fid="539354" lims:id="539354" level="1"><TitleText>Zone 7</TitleText></Heading><Provision lims:inforce-start-date="2010-06-10" lims:fid="539355" lims:id="539355" format-ref="indent-0-0" language-align="yes" list-item="no"><Text>COMMENÇANT au point 70°00′ de latitude, 93°20′ de longitude; DE LÀ le long du parallèle 70°00′ de latitude jusqu’à 104°50′ de longitude; DE LÀ le long du méridien 104°50′ de longitude jusqu’à 66°20′ de latitude; DE LÀ le long du parallèle 66°20′ de latitude jusqu’à 93°20′ de longitude; DE LÀ le long du méridien 93°20′ jusqu’au point de départ.</Text></Provision><Heading lims:inforce-start-date="2010-06-10" lims:fid="539356" lims:id="539356" level="1"><TitleText>Zone 8</TitleText></Heading><Provision lims:inforce-start-date="2010-06-10" lims:fid="539357" lims:id="539357" format-ref="indent-0-0" language-align="yes" list-item="no"><Text>COMMENÇANT au point 64°20′ de latitude, 93°20′ de longitude; DE LÀ le long du parallèle 64°20′ de latitude jusqu’à son point d’intersection le plus à l’ouest avec le littoral de l’île Baffin, à la péninsule Foxe; DE LÀ le long du littoral ouest de l’île Baffin jusqu’à son point d’intersection le plus au sud avec la longitude 84°00′; DE LÀ le long du méridien 84°00′ de longitude jusqu’à 67°00′ de latitude; DE LÀ le long du parallèle 67°00′ de latitude jusqu’à 93°20′ de longitude; DE LÀ le long du méridien 93°20′ de longitude jusqu’au point de départ.</Text></Provision><Heading lims:inforce-start-date="2010-06-10" lims:fid="539358" lims:id="539358" level="1"><TitleText>Zone 9</TitleText></Heading><Provision lims:inforce-start-date="2010-06-10" lims:fid="539359" lims:id="539359" format-ref="indent-0-0" language-align="yes" list-item="no"><Text>Commençant au point d’intersection le plus à l’est de la latitude 66°35′ avec le littoral de l’île de Baffin, près du cap Dyer; de là, le long du parallèle 66°35′ de latitude jusqu’à la limite au large dans le détroit de Davis; de là, le long de la limite au large jusqu’à 73°35′ de latitude dans la baie de Baffin; de là, le long d’une ligne jusqu’au point d’intersection le plus à l’est de la latitude 72°30′ avec le littoral de l’île de Baffin, près du cap Macculloch; de là, le long du littoral est de l’île de Baffin jusqu’au point de départ.</Text></Provision><Heading lims:inforce-start-date="2010-06-10" lims:fid="539360" lims:id="539360" level="1"><TitleText>Zone 10</TitleText></Heading><Provision lims:inforce-start-date="2010-06-10" lims:fid="539361" lims:id="539361" format-ref="indent-0-0" language-align="yes" list-item="no"><Text>COMMENÇANT au point 66°35′ de latitude, 69°00′ de longitude; DE LÀ le long du méridien 69°00′ de longitude jusqu’à 64°20′ de latitude; DE LÀ le long du parallèle 64°20′ de latitude jusqu’à la limite au large dans le détroit de Davis; DE LÀ le long de la limite au large jusqu’à 66°35′ de latitude dans le détroit de Davis; DE LÀ le long du parallèle 66°35′ de latitude jusqu’au point de départ.</Text></Provision><Heading lims:inforce-start-date="2010-06-10" lims:fid="539362" lims:id="539362" level="1"><TitleText>Zone 11</TitleText></Heading><Provision lims:inforce-start-date="2010-06-10" lims:fid="539363" lims:id="539363" format-ref="indent-0-0" language-align="yes" list-item="no"><Text>COMMENÇANT au point 70°00′ de latitude, 104°50′ de longitude; DE LÀ le long du parallèle 70°00′ de latitude jusqu’à 110°00′ de longitude; DE LÀ le long d’une ligne jusqu’au point 72°45′ de latitude, 117°20′ de longitude; DE LÀ le long du parallèle 72°45′ de latitude jusqu’à son point d’intersection le plus à l’est avec le littoral de l’île Banks; DE LÀ le long du littoral sud-est de l’île Banks jusqu’à son point d’intersection le plus au sud avec la longitude 123°00′, près du cap Lambton; DE LÀ le long d’une ligne jusqu’au point 66°20′ de latitude, 121°45′ de longitude; DE LÀ le long du parallèle 66°20′ de latitude jusqu’à 104°50′ de longitude; DE LÀ le long du méridien 104°50′ de longitude jusqu’au point de départ.</Text></Provision><Heading lims:inforce-start-date="2010-06-10" lims:fid="539364" lims:id="539364" level="1"><TitleText>Zone 12</TitleText></Heading><Provision lims:inforce-start-date="2010-06-10" lims:fid="539365" lims:id="539365" format-ref="indent-0-0" language-align="yes" list-item="no"><Text>COMMENÇANT au point 70°30′ de latitude, 141°00′ de longitude; DE LÀ le long du méridien 141°00′ de longitude jusqu’à 66°20′ de latitude; DE LÀ le long du parallèle 66°20′ de latitude jusqu’à 121°45′ de longitude; DE LÀ le long d’une ligne jusqu’au point d’intersection le plus au sud de la longitude 123°00′ et du littoral de l’île Banks, près du cap Lambton; DE LÀ le long du littoral sud-ouest de l’île Banks jusqu’à son point d’intersection le plus à l’ouest avec la latitude 73°30′, près de l’île Bernard; DE LÀ le long du parallèle 73°30′ de latitude jusqu’à 125°00′ de longitude; DE LÀ le long d’une ligne jusqu’au point 72°00′ de latitude, 127°00′ de longitude; DE LÀ le long d’une ligne jusqu’au point 70°30′ de latitude, 138°00′ de longitude; DE LÀ le long du parallèle 70°30′ de latitude jusqu’au point de départ, à l’exclusion des eaux suivantes :</Text><Provision lims:inforce-start-date="2010-06-10" lims:fid="539366" lims:id="539366" format-ref="indent-1-1" language-align="no" list-item="no"><Label>a)</Label><Text>les eaux de la baie Shallow, de la baie Shoalwater, de la baie Trent et de la baie Mackenzie jusqu’à une ligne au large tirée le long du parallèle 69°00′ de latitude; et</Text></Provision><Provision lims:inforce-start-date="2010-06-10" lims:fid="539367" lims:id="539367" format-ref="indent-1-1" language-align="no" list-item="no"><Label>b)</Label><Text>les eaux de la baie Kugmallit jusqu’à une ligne au large tirée le long du parallèle 69°31′ de latitude.</Text></Provision></Provision><Heading lims:inforce-start-date="2010-06-10" lims:fid="539368" lims:id="539368" level="1"><TitleText>Zone 13</TitleText></Heading><Provision lims:inforce-start-date="2010-06-10" lims:fid="539369" lims:id="539369" format-ref="indent-0-0" language-align="yes" list-item="no"><Text>Commençant au point d’intersection de la latitude 76°30′ avec la limite au large dans la baie de Baffin; de là, le long d’une ligne jusqu’à 75°00′ de latitude, 82°00′ de longitude; de là, le long du parallèle 75°00′ de latitude jusqu’à 95°00′ de longitude; de là, le long du méridien 95°00′ de longitude jusqu’à 73°45′ de latitude; de là, le long du parallèle 73°45′ de latitude jusqu’à 87°00′ de longitude; de là, le long du méridien 87°00′ de longitude jusqu’à 70°50′ de latitude; de là, le long du parallèle 70°50′ de latitude jusqu’à 84°00′ de longitude; de là, le long d’une ligne jusqu’au point d’intersection le plus à l’est de la latitude 72°30′ avec le littoral de l’île de Baffin, près du cap Macculloch; de là, le long d’une ligne jusqu’au point d’intersection de la latitude 73°35′ avec la limite au large dans la baie de Baffin; de là, le long de la limite au large jusqu’au point de départ.</Text></Provision><Heading lims:inforce-start-date="2010-06-10" lims:fid="539370" lims:id="539370" level="1"><TitleText>Zone 14</TitleText></Heading><Provision lims:inforce-start-date="2010-06-10" lims:fid="539371" lims:id="539371" format-ref="indent-0-0" language-align="yes" list-item="no"><Text>COMMENÇANT au point 60°00′ de latitude, 77°10′ de longitude; DE LÀ le long d’une ligne jusqu’au point d’intersection le plus à l’ouest de la latitude 64°20′ et du littoral de l’île Baffin, à la péninsule Foxe; DE LÀ le long du parallèle 64°20′ de latitude jusqu’à son point d’intersection le plus à l’ouest avec le littoral de l’île Southampton; DE LÀ le long du littoral ouest de l’île Southampton jusqu’à son point d’intersection le plus au sud avec la longitude 87°10′, près du cap Kendall; DE LÀ le long d’une ligne jusqu’au point 60°00′ de latitude, 92°00′ de longitude; DE LÀ le long du parallèle 60°00′ de latitude jusqu’au point de départ.</Text></Provision><Heading lims:inforce-start-date="2010-06-10" lims:fid="539372" lims:id="539372" level="1"><TitleText>Zone 15</TitleText></Heading><Provision lims:inforce-start-date="2010-06-10" lims:fid="539373" lims:id="539373" format-ref="indent-0-0" language-align="yes" list-item="no"><Text>COMMENÇANT au point 60°00′ de latitude, 77°10′ de longitude; DE LÀ le long du parallèle 60°00′ de latitude jusqu’à la limite au large dans la mer du Labrador; DE LÀ le long de la limite au large jusqu’à 64°20′ de latitude; DE LÀ le long du parallèle 64°20′ de latitude jusqu’à 69°00′ de longitude; DE LÀ le long du méridien 69°00′ de longitude jusqu’à 65°00′ de latitude; DE LÀ le long du parallèle 65°00′ de latitude jusqu’à 75°00′ de longitude; DE LÀ le long d’une ligne jusqu’au point d’intersection le plus à l’ouest de la latitude 64°20′ et du littoral de l’île Baffin, à la péninsule Foxe; DE LÀ le long d’une ligne jusqu’au point de départ.</Text></Provision><Heading lims:inforce-start-date="2010-06-10" lims:fid="539374" lims:id="539374" level="1"><TitleText>Zone 16</TitleText></Heading><Provision lims:inforce-start-date="2010-06-10" lims:fid="539375" lims:id="539375" format-ref="indent-0-0" language-align="yes" list-item="no"><Text>COMMENÇANT au point 60°00′ de latitude, 92°00′ de longitude; DE LÀ le long d’une ligne jusqu’au point d’intersection le plus au sud de la longitude 87°10′ et du littoral ouest de l’île Southampton, près du cap Kendall; DE LÀ le long du littoral ouest de l’île Southampton jusqu’à son point d’intersection le plus à l’ouest avec la latitude 64°20′ DE LÀ le long du parallèle 64°20′ de latitude jusqu’à 93°20′ de longitude; DE LÀ le long d’une ligne jusqu’au point 60°00′ de latitude, 95°00′ de longitude; DE LÀ le long du parallèle 60°00′ de latitude jusqu’au point de départ.</Text></Provision><Provision lims:inforce-start-date="2010-06-10" lims:fid="539376" lims:id="539376" format-ref="indent-0-0" language-align="yes" list-item="no"><Text><Emphasis style="italic">Note</Emphasis> : Dans les descriptions ci-dessus des zones de contrôle de la sécurité de la navigation, les indications suivantes s’appliquent :</Text><Provision lims:inforce-start-date="2010-06-10" lims:fid="539377" lims:id="539377" format-ref="indent-1-1" language-align="no" list-item="no"><Label>a)</Label><Text>toutes les lignes sont celles qui sont les plus courtes entre les points indiqués, sauf indication contraire;</Text></Provision><Provision lims:inforce-start-date="2010-06-10" lims:fid="539378" lims:id="539378" format-ref="indent-1-1" language-align="no" list-item="no"><Label>b)</Label><Text><DefinedTermFr>littoral</DefinedTermFr> s’entend de la limite extrême du littoral;</Text></Provision><Provision lims:inforce-start-date="2010-06-10" lims:fid="539379" lims:id="539379" format-ref="indent-1-1" language-align="no" list-item="no"><Label>c)</Label><Text>les noms géographiques sont conformes à l’<XRefExternal reference-type="other">Atlas du Canada</XRefExternal> publié par le ministère des Ressources naturelles.</Text></Provision></Provision><HistoricalNote><HistoricalNoteSubItem lims:inforce-start-date="2010-06-10" lims:fid="539381" lims:id="539381">DORS/2010-131, art. 2 à 7</HistoricalNoteSubItem></HistoricalNote></Schedule><Schedule lims:inforce-start-date="2010-06-10" lims:lastAmendedDate="2010-06-10" lims:fid="539382" lims:id="539382" spanlanguages="yes"><ScheduleFormHeading lims:inforce-start-date="2010-06-10" lims:fid="539383" lims:id="539383"><Label>ANNEXE 2</Label><OriginatingRef>(article 3)</OriginatingRef><TitleText>Zones de contrôle de la sécurité de la navigation</TitleText></ScheduleFormHeading><ImageGroup lims:inforce-start-date="2010-06-10" lims:fid="539384" lims:id="539384" position="center" width="42pc"><AlternateText>Carte des eaux arctiques du Canada indiquant les seize zones de contrôle de la sécurité de la navigation</AlternateText><Image source="CRC356img\CRC356_f002.png" /></ImageGroup><HistoricalNote><HistoricalNoteSubItem lims:inforce-start-date="2010-06-10" lims:fid="539386" lims:id="539386">DORS/2010-131, art. 8</HistoricalNoteSubItem></HistoricalNote></Schedule></Regulation>