<?xml version="1.0" encoding="utf-8"?><Regulation lims:pit-date="2017-06-20" hasPreviousVersion="true" lims:lastAmendedDate="2017-06-20" lims:current-date="2019-06-21" lims:inforce-start-date="2017-06-20" lims:fid="863218" lims:id="863218" regulation-type="SOR" xml:lang="fr" xmlns:lims="http://justice.gc.ca/lims"><Identification lims:inforce-start-date="2017-06-20" lims:fid="863219" lims:id="863219"><InstrumentNumber>DORS/82-832</InstrumentNumber><RegistrationDate><Date><YYYY>1982</YYYY><MM>9</MM><DD>7</DD></Date></RegistrationDate><ConsolidationDate lims:inforce-start-date="2017-06-20"><Date><YYYY>2019</YYYY><MM>6</MM><DD>22</DD></Date></ConsolidationDate><EnablingAuthority lims:inforce-start-date="2017-06-20" lims:fid="863221" lims:id="863221"><XRefExternal reference-type="act" link="A-12">LOI SUR LA PRÉVENTION DE LA POLLUTION DES EAUX ARCTIQUES</XRefExternal></EnablingAuthority><ShortTitle lims:inforce-start-date="2017-06-20" lims:fid="863222" lims:id="863222">Règlement de 1982 sur la pollution, à titre expérimental, des eaux arctiques (Dome Petroleum)</ShortTitle><LongTitle lims:inforce-start-date="2017-06-20" lims:fid="863223" lims:id="863223">Règlement sur le déversement de pétrole dans les eaux arctiques, à titre expérimental, par la Dome Petroleum Limited</LongTitle><RegulationMakerOrder><RegulationMaker>C.P.</RegulationMaker><OrderNumber>1982-2631</OrderNumber><Date><YYYY>1982</YYYY><MM>9</MM><DD>3</DD></Date></RegulationMakerOrder></Identification><Repealed lims:inforce-start-date="2017-06-20" lims:fid="863224" lims:id="863224">[Abrogé, DORS/2017-135, art. 1]</Repealed><Body lims:inforce-start-date="2017-06-20" lims:fid="863225" lims:id="863225"><Heading lims:inforce-start-date="2017-06-20" lims:fid="863226" lims:id="863226" level="1"><TitleText>Titre abrégé</TitleText><Note>[Abrogée, DORS/2017-135, art. 1]</Note></Heading><Section lims:inforce-start-date="2017-06-20" lims:lastAmendedDate="2017-06-20" lims:fid="863227" lims:id="863227"><Label>1</Label><Text><Repealed>[Abrogé, DORS/2017-135, art. 1]</Repealed></Text></Section><Heading lims:inforce-start-date="2017-06-20" lims:fid="863228" lims:id="863228" level="1"><TitleText>Définition</TitleText><Note>[Abrogée, DORS/2017-135, art. 1]</Note></Heading><Section lims:inforce-start-date="2017-06-20" lims:lastAmendedDate="2017-06-20" lims:fid="863229" lims:id="863229"><Label>2</Label><Text><Repealed>[Abrogé, DORS/2017-135, art. 1]</Repealed></Text></Section><Heading lims:inforce-start-date="2017-06-20" lims:fid="863230" lims:id="863230" level="1"><TitleText>Déversement de pétrole</TitleText><Note>[Abrogée, DORS/2017-135, art. 1]</Note></Heading><Section lims:inforce-start-date="2017-06-20" lims:lastAmendedDate="2017-06-20" lims:fid="863231" lims:id="863231"><Label>3</Label><Text><Repealed>[Abrogé, DORS/2017-135, art. 1]</Repealed></Text></Section><Heading lims:inforce-start-date="2017-06-20" lims:fid="863232" lims:id="863232" level="1"><TitleText>Conditions</TitleText><Note>[Abrogée, DORS/2017-135, art. 1]</Note></Heading><Section lims:inforce-start-date="2017-06-20" lims:lastAmendedDate="2017-06-20" lims:fid="863233" lims:id="863233"><Label>4</Label><Text><Repealed>[Abrogé, DORS/2017-135, art. 1]</Repealed></Text></Section><Section lims:inforce-start-date="2017-06-20" lims:lastAmendedDate="2017-06-20" lims:fid="863234" lims:id="863234"><Label>5</Label><Text><Repealed>[Abrogé, DORS/2017-135, art. 1]</Repealed></Text></Section></Body><Order lims:inforce-start-date="2017-06-20" lims:fid="863235" lims:id="863235"><Provision lims:inforce-start-date="2017-06-20" lims:fid="863236" lims:id="863236"><Text><Repealed>[Abrogé, DORS/2017-135, art. 1]</Repealed></Text></Provision></Order></Regulation>