<?xml version="1.0" encoding="utf-8"?><Regulation lims:pit-date="2006-03-22" lims:lastAmendedDate="2006-03-22" lims:current-date="2019-06-21" lims:inforce-start-date="2006-03-22" lims:fid="854561" lims:id="854561" gazette-part="II" regulation-type="SOR" xml:lang="fr" xmlns:lims="http://justice.gc.ca/lims"><Identification lims:inforce-start-date="2006-03-22" lims:fid="854562" lims:id="854562"><InstrumentNumber>DORS/79-555</InstrumentNumber><RegistrationDate><Date><YYYY>1979</YYYY><MM>7</MM><DD>27</DD></Date></RegistrationDate><ConsolidationDate lims:inforce-start-date="2006-03-22"><Date><YYYY>2019</YYYY><MM>6</MM><DD>22</DD></Date></ConsolidationDate><EnablingAuthority lims:inforce-start-date="2006-03-22" lims:fid="854564" lims:id="854564"><XRefExternal reference-type="act" link="C-22">LOI SUR LE CONSEIL DE LA RADIODIFFUSION ET DES TÉLÉCOMMUNICATIONS CANADIENNES</XRefExternal></EnablingAuthority><ShortTitle lims:inforce-start-date="2006-03-22" lims:fid="854565" lims:id="854565">Règlement sur les tarifs du CRTC</ShortTitle><LongTitle lims:inforce-start-date="2006-03-22" lims:fid="854566" lims:id="854566">Règlement concernant la forme et la publication des tarifs</LongTitle></Identification><Order lims:inforce-start-date="2006-03-22" lims:fid="854567" lims:id="854567"><Provision lims:inforce-start-date="2006-03-22" lims:fid="854568" lims:id="854568" format-ref="indent-0-0" language-align="yes"><Text>Le Conseil de la radiodiffusion et des télécommunications canadiennes,</Text><Provision lims:inforce-start-date="2006-03-22" lims:fid="854569" lims:id="854569" format-ref="indent-1-1"><Label>(a)</Label><Text>conformément à l’article 17 de la <XRefExternal reference-type="act" link="C-22">Loi sur le Conseil de la radiodiffusion et des télécommunications canadiennes</XRefExternal>, annule par la présente le <XRefExternal reference-type="regulation">Règlement régissant l’établissement, le dépôt et l’affichage des tarifs télégraphiques et téléphoniques par les compagnies de télégraphe et de téléphone (Circulaire de tarif nº 3)</XRefExternal> émises par la Commission des transports du Canada dans l’Ordonnance générale nº 843 du 1<Sup>er</Sup> avril 1959; et,</Text></Provision><Provision lims:inforce-start-date="2006-03-22" lims:fid="854570" lims:id="854570" format-ref="indent-1-1"><Label>(b)</Label><Text>conformément au paragraphe 14(2) de la <XRefExternal reference-type="act" link="C-22">Loi sur le Conseil de la radiodiffusion et des télécommunications canadiennes</XRefExternal> et à l’article 270, aux paragraphes 320(3), 320(6) et 321(5) de la <XRefExternal reference-type="act">Loi sur les chemins de fer</XRefExternal> énonce, ci-joint, le <XRefExternal reference-type="regulation" link="DORS-79-555">Règlement concernant la forme et la publication des tarifs</XRefExternal> qui entreront en vigueur à compter du 20 juillet 1979, sauf les paragraphes 4(3), 4(4) et 4(6) qui entreront en vigueur le 1<Sup>er</Sup> juillet 1980.</Text></Provision></Provision><Provision lims:inforce-start-date="2006-03-22" lims:fid="854571" lims:id="854571" format-ref="indent-0-0" language-align="yes"><Text>Ottawa, le 20 juillet 1979</Text></Provision></Order><Body lims:inforce-start-date="2006-03-22" lims:fid="854572" lims:id="854572"><Heading lims:inforce-start-date="2006-03-22" lims:fid="854573" lims:id="854573" level="1"><TitleText>Titre abrégé</TitleText></Heading><Section lims:inforce-start-date="2006-03-22" lims:lastAmendedDate="2006-03-22" lims:fid="854574" lims:id="854574"><Label>1</Label><Text>Le présent règlement peut être cité sous le titre : <XRefExternal reference-type="regulation" link="DORS-79-555">Règlement sur les tarifs du CRTC</XRefExternal>.</Text></Section><Heading lims:inforce-start-date="2006-03-22" lims:fid="854575" lims:id="854575" level="1"><TitleText>Interprétation</TitleText></Heading><Section lims:inforce-start-date="2006-03-22" lims:lastAmendedDate="2006-03-22" lims:fid="854576" lims:id="854576"><Label>2</Label><Text>Dans le présent règlement, tous les termes ont le même sens que dans les <XRefExternal reference-type="regulation" link="DORS-79-554">Règles de procédure du CRTC en matière de télécommunications</XRefExternal>.</Text></Section><Heading lims:inforce-start-date="2006-03-22" lims:fid="854577" lims:id="854577" level="1"><TitleText>Approbation des tarifs</TitleText></Heading><Section lims:inforce-start-date="2006-03-22" lims:lastAmendedDate="2006-03-22" lims:fid="854578" lims:id="854578"><Label>3</Label><Text>Les tarifs d’une société réglementée doivent, avant leur entrée en vigueur, être approuvés par le Conseil.</Text></Section><Heading lims:inforce-start-date="2006-03-22" lims:fid="854579" lims:id="854579" level="1"><TitleText>Présentation des tarifs</TitleText></Heading><Section lims:inforce-start-date="2006-03-22" lims:lastAmendedDate="2006-03-22" lims:fid="854580" lims:id="854580"><Label>4</Label><Subsection lims:inforce-start-date="2006-03-22" lims:fid="854581" lims:id="854581"><Label>(1)</Label><Text>Les tarifs d’une société réglementée sont présentés sous forme de cahiers à feuilles mobiles de 21,5 centimètres sur 28 centimètres et sont reproduits lisiblement par un procédé assurant l’exactitude de toutes les copies.</Text></Subsection><Subsection lims:inforce-start-date="2006-03-22" lims:fid="854582" lims:id="854582"><Label>(2)</Label><Text>Il est interdit de modifier ou d’effacer le texte original des tarifs déposés auprès du Conseil ou mis à la disposition du public.</Text></Subsection><Subsection lims:inforce-start-date="2006-03-22" lims:fid="854583" lims:id="854583"><Label>(3)</Label><Text>Les tarifs sont numérotés selon la série de numéros appropriée du tableau du présent article, le sigle « CRTC » apparaissant devant chaque numéro.</Text></Subsection><Subsection lims:inforce-start-date="2006-03-22" lims:fid="854584" lims:id="854584"><Label>(4)</Label><Text>L’index des tarifs publié selon l’article 6 et, le cas échéant, le Tarif général, sont respectivement les premier et deuxième tarifs à être numérotés selon le paragraphe (3).</Text></Subsection><Subsection lims:inforce-start-date="2006-03-22" lims:fid="854585" lims:id="854585"><Label>(5)</Label><Text>Une société réglementée non visée dans le tableau du présent article peut, par requête <Language xml:lang="la">ex parte</Language>, demander au Conseil de lui attribuer une série de numéros.</Text></Subsection><Subsection lims:inforce-start-date="2006-03-22" lims:fid="854586" lims:id="854586"><Label>(6)</Label><Text>Lorsque le Conseil établit qu’une société réglementée dessert une proportion importante de ses abonnés dans les deux langues officielles, tous les tarifs qu’elle dépose auprès de lui ou met à la disposition du public doivent être publiés dans les deux langues officielles.</Text><TableGroup lims:inforce-start-date="2006-03-22" lims:fid="854587" lims:id="854587" pointsize="9" topmarginspacing="4"><Caption lims:inforce-start-date="2006-03-22" lims:fid="854588" lims:id="854588" position="over">TABLEAU</Caption><table lims:inforce-start-date="2006-03-22" lims:fid="854589" lims:id="854589" frame="topbot"><tgroup lims:inforce-start-date="2006-03-22" lims:fid="854590" lims:id="854590" cols="2"><colspec colname="1" colwidth="242.07*" /><colspec colname="2" colwidth="225.93*" /><thead lims:inforce-start-date="2006-03-22" lims:fid="854591" lims:id="854591"><row topmarginspacing="6"><entry colname="1" colsep="0" rowsep="0" valign="top"><Emphasis style="italic">Société réglementée</Emphasis></entry><entry colname="2" colsep="0" rowsep="0" valign="top"><Emphasis style="italic">Série attribuée</Emphasis></entry></row></thead><tbody lims:inforce-start-date="2006-03-22" lims:fid="854592" lims:id="854592"><row topmarginspacing="6"><entry colname="1" colsep="0" rowsep="0" valign="top">British Columbia Telephone Company</entry><entry colname="2" colsep="0" rowsep="0" valign="bottom">CRTC 1000-CRTC 1999</entry></row><row topmarginspacing="6"><entry colname="1" colsep="0" rowsep="0" valign="top">Terra Nova Telecommunications</entry><entry colname="2" colsep="0" rowsep="0" valign="bottom">CRTC 2000-CRTC 2999</entry></row><row topmarginspacing="6"><entry colname="1" colsep="0" rowsep="0" valign="top">Northwest Telecommunications</entry><entry colname="2" colsep="0" rowsep="0" valign="bottom">CRTC 3000-CRTC 3999</entry></row><row topmarginspacing="6"><entry colname="1" colsep="0" rowsep="0" valign="top">Télécommunications du CN</entry><entry colname="2" colsep="0" rowsep="0" valign="bottom">CRTC 4000-CRTC 4999</entry></row><row topmarginspacing="6"><entry colname="1" colsep="0" rowsep="0" valign="top">Télécommunications du CP</entry><entry colname="2" colsep="0" rowsep="0" valign="bottom">CRTC 5000-CRTC 5999</entry></row><row topmarginspacing="6"><entry colname="1" colsep="0" rowsep="0" valign="top">Bell Canada</entry><entry colname="2" colsep="0" rowsep="0" valign="bottom">CRTC 6000-CRTC 7999</entry></row><row topmarginspacing="6"><entry colname="1" colsep="0" rowsep="1" valign="top">Télésat Canada</entry><entry colname="2" colsep="0" rowsep="1" valign="bottom">CRTC 8000-CRTC 8999</entry></row></tbody></tgroup></table></TableGroup></Subsection></Section><Heading lims:inforce-start-date="2006-03-22" lims:fid="854593" lims:id="854593" level="1"><TitleText>Contenu des tarifs</TitleText></Heading><Section lims:inforce-start-date="2006-03-22" lims:lastAmendedDate="2006-03-22" lims:fid="854594" lims:id="854594"><Label>5</Label><Subsection lims:inforce-start-date="2006-03-22" lims:fid="854595" lims:id="854595"><Label>(1)</Label><Text>Les tarifs d’une société réglementée comportent un index détaillé et complet des sujets traités, donnant par ordre alphabétique l’endroit exact des renseignements recherchés, et précisant la page et le numéro des articles applicables.</Text></Subsection><Subsection lims:inforce-start-date="2006-03-22" lims:fid="854596" lims:id="854596"><Label>(2)</Label><Text>L’index peut être omis si la page titre ou la disposition du tarif indique clairement son contenu.</Text></Subsection><Subsection lims:inforce-start-date="2006-03-22" lims:fid="854597" lims:id="854597"><Label>(3)</Label><Text>Chaque page d’un tarif porte</Text><Paragraph lims:inforce-start-date="2006-03-22" lims:fid="854598" lims:id="854598"><Label>a)</Label><Text>au-dessus d’une ligne horizontale tirée dans le coin supérieur gauche, la raison sociale de la société réglementée qui tarife et, dans le coin supérieur droit, le numéro assigné au tarif, en caractères gras;</Text></Paragraph><Paragraph lims:inforce-start-date="2006-03-22" lims:fid="854599" lims:id="854599"><Label>b)</Label><Text>au-dessous d’une ligne horizontale tirée dans le coin inférieur gauche, la date de dépôt de la demande d’approbation de la page du tarif en cause et, dans le coin inférieur droit, la date d’entrée en vigueur; et</Text></Paragraph><Paragraph lims:inforce-start-date="2006-03-22" lims:fid="854600" lims:id="854600"><Label>c)</Label><Text>au centre de la partie inférieure, un renvoi à l’ordonnance ou à la décision appropriée du Conseil, par exemple :</Text><Provision lims:inforce-start-date="2006-03-22" lims:fid="854601" lims:id="854601" format-ref="indent-2-2" language-align="no" list-item="no"><Text>« Approuvé par l’Ordonnance Télécomm. CRTC 78-43 du 16 janvier 1978 » ou « Cf. Décision Télécomm. CRTC 78-7 du 10 août 1978 ».</Text></Provision></Paragraph></Subsection><Subsection lims:inforce-start-date="2006-03-22" lims:fid="854602" lims:id="854602"><Label>(4)</Label><Text>Les règlements généraux d’une société réglementée énonçant les conditions de prestation des services et du matériel décrits dans ses tarifs approuvés sont inclus au début de son Tarif général.</Text></Subsection><Subsection lims:inforce-start-date="2006-03-22" lims:fid="854603" lims:id="854603"><Label>(5)</Label><Text>En l’absence d’un Tarif général, les règlements généraux visés au paragraphe (4) sont inclus dans l’un des tarifs approuvés de la société réglementée, et tous les autres tarifs approuvés comportent un renvoi, par numéro CRTC, au tarif reproduisant les règlements généraux.</Text></Subsection><Subsection lims:inforce-start-date="2006-03-22" lims:fid="854604" lims:id="854604"><Label>(6)</Label><Text>Chaque tarif expose clairement les règles et autres dispositions réglementaires de la société, leur titre ou leur sujet étant inscrits en caractères distinctifs; il comporte en outre un renvoi à tout autre tarif applicable.</Text></Subsection><Subsection lims:inforce-start-date="2006-03-22" lims:fid="854605" lims:id="854605"><Label>(7)</Label><Text>Les termes utilisés dans un tarif peuvent être définis dans une liste alphabétique distincte et, sauf indication contraire, ces définitions régissent tous les articles du tarif.</Text></Subsection><Subsection lims:inforce-start-date="2006-03-22" lims:fid="854606" lims:id="854606"><Label>(8)</Label><Text>Lorsque les définitions visées au paragraphe (7) s’appliquent à d’autres tarifs, le numéro du tarif CRTC en cause est indiqué dans ces autres tarifs.</Text></Subsection></Section><Heading lims:inforce-start-date="2006-03-22" lims:fid="854607" lims:id="854607" level="1"><TitleText>Index des tarifs</TitleText></Heading><Section lims:inforce-start-date="2006-03-22" lims:lastAmendedDate="2006-03-22" lims:fid="854608" lims:id="854608"><Label>6</Label><Text>Une société réglementée doit publier de la même manière qu’un tarif, un index complet de ses tarifs approuvés et de ses accords en vigueur, divisé en trois sections comme suit :</Text><Paragraph lims:inforce-start-date="2006-03-22" lims:fid="854609" lims:id="854609"><Label>a)</Label><Text>une liste numérique complète de ses propres tarifs, numérotés selon le paragraphe 4(3);</Text></Paragraph><Paragraph lims:inforce-start-date="2006-03-22" lims:fid="854610" lims:id="854610"><Label>b)</Label><Text>une liste descriptive complète des tarifs des autres sociétés qu’elle utilise pour établir les taxes et les frais de service d’une ligne continue exploitée conjointement avec ces sociétés;</Text></Paragraph><Paragraph lims:inforce-start-date="2006-03-22" lims:fid="854611" lims:id="854611"><Label>c)</Label><Text>une liste descriptive complète des accords approuvés qu’elle a avec d’autres sociétés.</Text></Paragraph></Section><Heading lims:inforce-start-date="2006-03-22" lims:fid="854612" lims:id="854612" level="1"><TitleText>Pagination des tarifs</TitleText></Heading><Section lims:inforce-start-date="2006-03-22" lims:lastAmendedDate="2006-03-22" lims:fid="854613" lims:id="854613"><Label>7</Label><Subsection lims:inforce-start-date="2006-03-22" lims:fid="854614" lims:id="854614"><Label>(1)</Label><Text>Sur la page titre de chaque tarif, la mention « Page titre originale » est inscrite dans le coin supérieur droit, et le numéro des pages suivantes est inscrit dans l’ordre dans le coin supérieur droit, immédiatement au-dessous du numéro CRTC du tarif, de la façon suivante : « Page 1 originale », « Page 2 originale », etc.</Text></Subsection><Subsection lims:inforce-start-date="2006-03-22" lims:fid="854615" lims:id="854615"><Label>(2)</Label><Text>Pour les tarifs d’au moins 10 pages, une société réglementée doit publier mensuellement les modifications; elle indique alors le numéro de modification applicable à chaque page.</Text></Subsection><Subsection lims:inforce-start-date="2006-03-22" lims:fid="854616" lims:id="854616"><Label>(3)</Label><Text>Pour les tarifs de moins de 10 pages, une société réglementée doit publier tous les trois mois les modifications; elle indique alors le numéro de modification applicable à chaque page.</Text></Subsection><Subsection lims:inforce-start-date="2006-03-22" lims:fid="854617" lims:id="854617"><Label>(4)</Label><Text>Lors d’une modification de tarif, la page concernée est réimprimée, désignée comme page modifiée et annotée à cet effet, par exemple,</Text><Provision lims:inforce-start-date="2006-03-22" lims:fid="854618" lims:id="854618" format-ref="centered" language-align="no" list-item="no"><Text>« 1<Sup>ère</Sup> révision de la page 1</Text></Provision><Provision lims:inforce-start-date="2006-03-22" lims:fid="854619" lims:id="854619" format-ref="centered" language-align="no" list-item="no" topmarginspacing="0"><Text>annule la page 1 originale »</Text></Provision><Provision lims:inforce-start-date="2006-03-22" lims:fid="854620" lims:id="854620" format-ref="centered" language-align="no" list-item="no"><Text>ou</Text></Provision><Provision lims:inforce-start-date="2006-03-22" lims:fid="854621" lims:id="854621" format-ref="centered" language-align="no" list-item="no"><Text>« 2<Sup>e</Sup> révision de la page 1</Text></Provision><Provision lims:inforce-start-date="2006-03-22" lims:fid="854622" lims:id="854622" format-ref="centered" language-align="no" list-item="no" topmarginspacing="0"><Text>annule la 1<Sup>ère</Sup> révision de la page 1 ».</Text></Provision></Subsection><Subsection lims:inforce-start-date="2006-03-22" lims:fid="854623" lims:id="854623"><Label>(5)</Label><Text>Les pages supplémentaires intercalées portent le numéro de la page qui les précède et sont numérotées sucessivement à la suite de cette dernière comme « Page 1A originale », « Page 1B originale », etc.</Text></Subsection><Subsection lims:inforce-start-date="2006-03-22" lims:fid="854624" lims:id="854624"><Label>(6)</Label><Text>Les pages ajoutées à la fin de la série originale du tarif sont numérotées successivement à la suite de cette dernière comme « Page ... originale », etc.</Text></Subsection><Subsection lims:inforce-start-date="2006-03-22" lims:fid="854625" lims:id="854625"><Label>(7)</Label><Text>Lorsqu’un sujet est porté à une autre page, le numéro de l’ancienne et de la nouvelle page est indiqué sur les deux pages. Ces indications sont supprimées dans les révisions subséquentes des pages en question.</Text></Subsection></Section><Heading lims:inforce-start-date="2006-03-22" lims:fid="854626" lims:id="854626" level="1"><TitleText>Délimitation des secteurs à tarif</TitleText></Heading><Section lims:inforce-start-date="2006-03-22" lims:lastAmendedDate="2006-03-22" lims:fid="854627" lims:id="854627"><Label>8</Label><Text>Les secteurs à tarif de base, les secteurs à tarif de localité et les autres secteurs où les frais de service local sont uniformes sont clairement délimités dans les tarifs au moyen d’une carte ou d’une description.</Text></Section><Heading lims:inforce-start-date="2006-03-22" lims:fid="854628" lims:id="854628" level="1"><TitleText>Étendue du service régional</TitleText></Heading><Section lims:inforce-start-date="2006-03-22" lims:lastAmendedDate="2006-03-22" lims:fid="854629" lims:id="854629"><Label>9</Label><Text>Lorsqu’une circonscription jouit d’un service régional, l’étendue du service est précisée dans les tarifs, ainsi que les facteurs de pondération utilisés pour le calcul des taxes afférentes.</Text></Section><Heading lims:inforce-start-date="2006-03-22" lims:fid="854630" lims:id="854630" level="1"><TitleText>Symboles</TitleText></Heading><Section lims:inforce-start-date="2006-03-22" lims:lastAmendedDate="2006-03-22" lims:fid="854631" lims:id="854631"><Label>10</Label><Subsection lims:inforce-start-date="2006-03-22" lims:fid="854632" lims:id="854632"><Label>(1)</Label><Text>Les symboles suivants ne servent qu’à indiquer les modifications apportées aux taxes, aux frais ou au libellé des tarifs :</Text><TableGroup lims:inforce-start-date="2006-03-22" lims:fid="854633" lims:id="854633" pointsize="9" topmarginspacing="4"><table lims:inforce-start-date="2006-03-22" lims:fid="854634" lims:id="854634" frame="none"><tgroup lims:inforce-start-date="2006-03-22" lims:fid="854635" lims:id="854635" cols="3"><colspec colname="col1" colwidth="0.13*" align="center" /><colspec colname="COLSPEC2" colwidth="0.13*" align="center" /><colspec colname="col2" colwidth="1.73*" /><tbody lims:inforce-start-date="2006-03-22" lims:fid="854636" lims:id="854636"><row><entry colsep="0" rowsep="0">♦</entry><entry colsep="0" rowsep="0">ou</entry><entry colsep="0" rowsep="0">(A)— augmentation;</entry></row><row><entry colsep="0" rowsep="0"><ImageGroup position="left" width=".5pc" float="top"><AlternateText>Cercle noir surmonté d’un petit carré noir</AlternateText><Image source="SOR-79-555img\SOR-79-555_ef001.png" /></ImageGroup></entry><entry colsep="0" rowsep="0">ou</entry><entry colsep="0" rowsep="0">(R)— réduction;</entry></row><row><entry colsep="0" rowsep="0">▲</entry><entry colsep="0" rowsep="0">ou</entry><entry colsep="0" rowsep="0">(C)— libellé modifié, taxes et frais inchangés;</entry></row><row><entry colsep="0" rowsep="0">●</entry><entry colsep="0" rowsep="0">ou</entry><entry colsep="0" rowsep="0">(NC)— taxes et frais inchangés;</entry></row><row><entry colsep="0" rowsep="0">*</entry><entry colsep="0" rowsep="0">ou</entry><entry colsep="0" rowsep="0">(N)— taxes ou frais nouveaux;</entry></row><row><entry colsep="0" rowsep="0">☐</entry><entry colsep="0" rowsep="0">ou</entry><entry colsep="0" rowsep="0">(S)— sujet publié de nouveau;</entry></row></tbody></tgroup></table></TableGroup></Subsection><Subsection lims:inforce-start-date="2006-03-22" lims:fid="854637" lims:id="854637"><Label>(2)</Label><Text>Les symboles reproduits au paragraphe (1) sont inscrits le plus près possible de la modification qu’ils désignent.</Text></Subsection></Section><Heading lims:inforce-start-date="2006-03-22" lims:fid="854638" lims:id="854638" level="1"><TitleText>Consultation des tarifs</TitleText></Heading><Section lims:inforce-start-date="2006-03-22" lims:lastAmendedDate="2006-03-22" lims:fid="854639" lims:id="854639"><Label>11</Label><Subsection lims:inforce-start-date="2006-03-22" lims:fid="854640" lims:id="854640"><Label>(1)</Label><Text>Une société réglementée conserve dans chacun de ses bureaux d’affaires un exemplaire de ses tarifs.</Text></Subsection><Subsection lims:inforce-start-date="2006-03-22" lims:fid="854641" lims:id="854641"><Label>(2)</Label><Text>Lorsqu’un tarif s’applique à plusieurs circonscriptions, le bureau d’affaires de la société réglementée qui est situé dans chacune d’elles ne conserve que la partie du tarif qui vise la circonscription.</Text></Subsection><Subsection lims:inforce-start-date="2006-03-22" lims:fid="854642" lims:id="854642"><Label>(3)</Label><Text>La société réglementée conserve un jeu complet de chacun de ses tarifs dans ses bureaux d’affaires d’au moins deux villes importantes du territoire qu’elle dessert.</Text></Subsection><Subsection lims:inforce-start-date="2006-03-22" lims:fid="854643" lims:id="854643"><Label>(4)</Label><Text>Les tarifs peuvent être consultés par le public aux bureaux d’affaires de la société réglementée pendant les heures ouvrables.</Text></Subsection><Subsection lims:inforce-start-date="2006-03-22" lims:fid="854644" lims:id="854644"><Label>(5)</Label><Text>Le responsable du bureau conservant les tarifs conformément au présent article doit, sur demande,</Text><Paragraph lims:inforce-start-date="2006-03-22" lims:fid="854645" lims:id="854645"><Label>a)</Label><Text>produire les tarifs désirés,</Text></Paragraph><Paragraph lims:inforce-start-date="2006-03-22" lims:fid="854646" lims:id="854646"><Label>b)</Label><Text>voir à ce que soit fournie gratuitement une copie d’un nombre maximum de 10 pages d’un tarif; et</Text></Paragraph><Paragraph lims:inforce-start-date="2006-03-22" lims:fid="854647" lims:id="854647"><Label>c)</Label><Text>voir à ce que soient fournies à un prix raisonnable des copies de toute page supplémentaire.</Text></Paragraph></Subsection></Section><Heading lims:inforce-start-date="2006-03-22" lims:fid="854648" lims:id="854648" level="1"><TitleText>Publication des tarifs</TitleText></Heading><Section lims:inforce-start-date="2006-03-22" lims:lastAmendedDate="2006-03-22" lims:fid="854649" lims:id="854649"><Label>12</Label><Subsection lims:inforce-start-date="2006-03-22" lims:fid="854650" lims:id="854650"><Label>(1)</Label><Text>Les tarifs d’une société réglementée sont fournis, en totalité ou en partie, par voie d’abonnement.</Text></Subsection><Subsection lims:inforce-start-date="2006-03-22" lims:fid="854651" lims:id="854651"><Label>(2)</Label><Text>Les frais et les conditions de l’abonnement visé au paragraphe (1) sont établis dans le Tarif général de la société ou, à défaut, dans l’un de ses tarifs en vigueur.</Text></Subsection></Section><Heading lims:inforce-start-date="2006-03-22" lims:fid="854652" lims:id="854652" level="1"><TitleText>Avis dans l’annuaire</TitleText></Heading><Section lims:inforce-start-date="2006-03-22" lims:lastAmendedDate="2006-03-22" lims:fid="854653" lims:id="854653"><Label>13</Label><Text>L’annuaire que fournit une société réglementée à ses abonnés contient un avis imprimé dont la forme est approuvée par le Conseil et qui contient les renseignements suivants :</Text><Paragraph lims:inforce-start-date="2006-03-22" lims:fid="854654" lims:id="854654"><Label>a)</Label><Text>un énoncé portant que les taxes, frais et modalités propres aux services et aux installations fournis par la société à l’abonné, sont régis par le Conseil et établis dans des tarifs approuvés par ce dernier;</Text></Paragraph><Paragraph lims:inforce-start-date="2006-03-22" lims:fid="854655" lims:id="854655"><Label>b)</Label><Text>un énoncé portant que les tarifs de la société applicables aux services fournis dans un secteur donné peuvent être consultés par le public à l’un des bureaux d’affaires de ce secteur pendant les heures ouvrables, et que le jeu complet des tarifs peut être consulté par le public dans les villes importantes visées au paragraphe 11(3) ainsi qu’aux bureaux du Conseil;</Text></Paragraph><Paragraph lims:inforce-start-date="2006-03-22" lims:fid="854656" lims:id="854656"><Label>c)</Label><Text>un énoncé portant que tout intéressé peut se procurer par voie d’abonnement un exemplaire des tarifs de la société;</Text></Paragraph><Paragraph lims:inforce-start-date="2006-03-22" lims:fid="854657" lims:id="854657"><Label>d)</Label><Text>un énoncé exposant la procédure applicable au traitement des plaintes et au règlement des différends entre les abonnés et la société, y compris</Text><Subparagraph lims:inforce-start-date="2006-03-22" lims:fid="854658" lims:id="854658"><Label>(i)</Label><Text>un bref exposé du genre de plaintes qu’un abonné peut adresser à la société,</Text></Subparagraph><Subparagraph lims:inforce-start-date="2006-03-22" lims:fid="854659" lims:id="854659"><Label>(ii)</Label><Text>les grandes lignes du recours initial que l’abonné peut choisir,</Text></Subparagraph><Subparagraph lims:inforce-start-date="2006-03-22" lims:fid="854660" lims:id="854660"><Label>(iii)</Label><Text>un énoncé de la procédure d’appel d’une décision au sein de la société, ainsi que l’adresse postale à utiliser lorsqu’il y a lieu;</Text></Subparagraph></Paragraph><Paragraph lims:inforce-start-date="2006-03-22" lims:fid="854661" lims:id="854661"><Label>e)</Label><Text>une déclaration portant que les plaintes qui n’ont pas été réglées à la satisfaction des parties conformément à l’alinéa d) peuvent être soumises par écrit au Conseil pour étude; et</Text></Paragraph><Paragraph lims:inforce-start-date="2006-03-22" lims:fid="854662" lims:id="854662"><Label>f)</Label><Text>un exposé, ou s’il y a lieu le texte intégral, des règlements généraux de la société, fixant les modalités de la prestation des services et du matériel décrits dans les tarifs approuvés par le Conseil.</Text></Paragraph></Section></Body></Regulation>